spock/__init__.py
spock/__init__.pyi
spock/_version.py
spock/args.py
spock/builder.py
spock/config.py
spock/config.pyi
spock/exceptions.py
spock/graph.py
spock/handlers.py
spock/helpers.py
spock/py.typed
spock/utils.py
spock/addons/__init__.py
spock/addons/s3/__init__.py
spock/addons/s3/configs.py
spock/addons/s3/utils.py
spock/addons/tune/__init__.py
spock/addons/tune/__init__.pyi
spock/addons/tune/ax.py
spock/addons/tune/builder.py
spock/addons/tune/config.py
spock/addons/tune/config.pyi
spock/addons/tune/interface.py
spock/addons/tune/optuna.py
spock/addons/tune/payload.py
spock/addons/tune/tuner.py
spock/backend/__init__.py
spock/backend/builder.py
spock/backend/config.py
spock/backend/config.pyi
spock/backend/custom.py
spock/backend/field_handlers.py
spock/backend/handler.py
spock/backend/help.py
spock/backend/payload.py
spock/backend/resolvers.py
spock/backend/saver.py
spock/backend/spaces.py
spock/backend/typed.py
spock/backend/utils.py
spock/backend/validators.py
spock/backend/wrappers.py
spock_config-3.1.0.dist-info/LICENSE.txt
spock_config-3.1.0.dist-info/METADATA
spock_config-3.1.0.dist-info/NOTICE.txt
spock_config-3.1.0.dist-info/WHEEL
spock_config-3.1.0.dist-info/top_level.txt
spock_config-3.1.0.dist-info/RECORD
