Metadata-Version: 2.1
Name: spock-config
Version: 3.1.0
Summary: Spock is a framework designed to help manage complex parameter configurations for Python applications
Home-page: https://github.com/fidelity/spock
Download-URL: https://github.com/fidelity/spock
Author: FMR LLC
Project-URL: Source, https://github.com/fidelity/spock
Project-URL: Documentation, https://fidelity.github.io/spock/
Project-URL: Bug Tracker, https://fidelity.github.io/spock/issues
Keywords: configuration,argparse,parameters,machine learning,deep learning,reproducibility,hyper-parameter tuning
Classifier: Development Status :: 5 - Production/Stable
Classifier: Intended Audience :: Developers
Classifier: Natural Language :: English
Classifier: License :: OSI Approved :: Apache Software License
Classifier: Programming Language :: Python :: 3
Classifier: Programming Language :: Python :: 3.6
Classifier: Programming Language :: Python :: 3.7
Classifier: Programming Language :: Python :: 3.8
Classifier: Programming Language :: Python :: 3.9
Classifier: Programming Language :: Python :: 3.10
Classifier: Operating System :: OS Independent
Classifier: Topic :: Scientific/Engineering
Classifier: Topic :: Scientific/Engineering :: Artificial Intelligence
Classifier: Topic :: Software Development :: Libraries :: Python Modules
Requires-Python: >=3.7
License-File: LICENSE.txt
License-File: NOTICE.txt
Requires-Dist: attrs ~=23.1
Requires-Dist: cryptography ~=37.0
Requires-Dist: GitPython ~=3.1
Requires-Dist: pytomlpp ~=1.0
Requires-Dist: pyYAML ~=6.0
Requires-Dist: setuptools ~=68.0 ; python_version == "3.7"
Requires-Dist: setuptools ~=68.1 ; python_version >= "3.8"
Provides-Extra: s3
Requires-Dist: hurry.filesize ~=0.9 ; extra == 's3'
Requires-Dist: boto3 ~=1.28 ; (python_version >= "3.7") and extra == 's3'
Requires-Dist: botocore ~=1.31 ; (python_version >= "3.7") and extra == 's3'
Requires-Dist: s3transfer ~=0.6 ; (python_version >= "3.7") and extra == 's3'
Provides-Extra: tune
Requires-Dist: optuna ~=3.3 ; extra == 'tune'
Requires-Dist: mypy-extensions ~=0.4 ; (python_version < "3.8") and extra == 'tune'
Requires-Dist: torch ~=1.13 ; (python_version <= "3.7") and extra == 'tune'
Requires-Dist: ax-platform ~=0.3.3 ; (python_version == "3.8") and extra == 'tune'
Requires-Dist: torch ~=2.0 ; (python_version >= "3.8") and extra == 'tune'
Requires-Dist: ax-platform ~=0.3.4 ; (python_version >= "3.9") and extra == 'tune'
